metermetrics/__init__.py
metermetrics/acc.py
metermetrics/cdf.py
metermetrics/counter.py
metermetrics/helper.py
metermetrics-0.2.0.dist-info/METADATA
metermetrics-0.2.0.dist-info/WHEEL
metermetrics-0.2.0.dist-info/top_level.txt
metermetrics-0.2.0.dist-info/RECORD
