Metadata-Version: 2.1
Name: metermetrics
Version: 0.2.0
Summary: Default template for PDM package
Author-email: svtter <svtter@qq.com>
License: not open
Requires-Python: >=3.9
Requires-Dist: numpy
Requires-Dist: pandas
Requires-Dist: matplotlib
Requires-Dist: seaborn
